markitdowng/__about__.py
markitdowng/__init__.py
markitdowng/__main__.py
markitdowng/_base_converter.py
markitdowng/_exceptions.py
markitdowng/_markitdown.py
markitdowng/_stream_info.py
markitdowng/_uri_utils.py
markitdowng/py.typed
markitdowng/converter_utils/__init__.py
markitdowng/converter_utils/docx/__init__.py
markitdowng/converter_utils/docx/pre_process.py
markitdowng/converter_utils/docx/math/__init__.py
markitdowng/converter_utils/docx/math/latex_dict.py
markitdowng/converter_utils/docx/math/omml.py
markitdowng/converters/__init__.py
markitdowng/converters/_audio_converter.py
markitdowng/converters/_bing_serp_converter.py
markitdowng/converters/_csv_converter.py
markitdowng/converters/_doc_intel_converter.py
markitdowng/converters/_docx_converter.py
markitdowng/converters/_epub_converter.py
markitdowng/converters/_exiftool.py
markitdowng/converters/_html_converter.py
markitdowng/converters/_image_converter.py
markitdowng/converters/_ipynb_converter.py
markitdowng/converters/_llm_caption.py
markitdowng/converters/_markdownify.py
markitdowng/converters/_outlook_msg_converter.py
markitdowng/converters/_pdf_converter.py
markitdowng/converters/_plain_text_converter.py
markitdowng/converters/_pptx_converter.py
markitdowng/converters/_rss_converter.py
markitdowng/converters/_transcribe_audio.py
markitdowng/converters/_wikipedia_converter.py
markitdowng/converters/_xlsx_converter.py
markitdowng/converters/_youtube_converter.py
markitdowng/converters/_zip_converter.py
markitdowng-1.0.1.dist-info/METADATA
markitdowng-1.0.1.dist-info/WHEEL
markitdowng-1.0.1.dist-info/entry_points.txt
markitdowng-1.0.1.dist-info/RECORD
